{
  "spec": "specs/fix-relay-streaming-bugs/02-specification.md",
  "slug": "fix-relay-streaming-bugs",
  "generatedAt": "2026-03-07T00:00:00.000Z",
  "mode": "full",
  "lastDecomposeDate": null,
  "tasks": [
    {
      "id": "1.1",
      "phase": 1,
      "phaseName": "Client-Side Bug Fixes",
      "subject": "[fix-relay-streaming-bugs] [P1] Guard sync_update invalidation during active streaming",
      "description": "Fix Bug 1 (message duplication) — Layer 1: Add a streaming guard to the sync_update EventSource listener in `apps/client/src/layers/features/chat/model/use-chat-session.ts`.\n\n## Problem\n\nThe `sync_update` handler at lines 270-273 calls `queryClient.invalidateQueries()` unconditionally. When a tool call completes, the SDK writes to the transcript, which fires `sync_update`. At the same time, the `done` event arrives and transitions status from `streaming` → `idle`. The history refetch triggered by `sync_update` races with the `done` transition: the seed effect (lines 210-217) runs with `isStreaming === false` and appends `history.slice(currentMessages.length)` — but `currentMessages` already contains the streamed text, so the same content is appended again.\n\n## Fix\n\nUse `statusRef` (already at line 134, kept in sync via a synchronous `useEffect` on every render) to read the current streaming status inside the listener closure. Closures capture values at creation time; `statusRef.current` gives the live value.\n\n**File:** `apps/client/src/layers/features/chat/model/use-chat-session.ts`\n**Lines to change:** 270-273\n\n```typescript\n// BEFORE:\neventSource.addEventListener('sync_update', () => {\n  queryClient.invalidateQueries({ queryKey: ['messages', sessionId, selectedCwdRef.current] });\n  queryClient.invalidateQueries({ queryKey: ['tasks', sessionId, selectedCwdRef.current] });\n});\n\n// AFTER:\neventSource.addEventListener('sync_update', () => {\n  // Skip invalidation during active streaming — relay_message events already update\n  // local state. The refetch would race with the done event and cause duplicates.\n  if (statusRef.current === 'streaming') return;\n  queryClient.invalidateQueries({ queryKey: ['messages', sessionId, selectedCwdRef.current] });\n  queryClient.invalidateQueries({ queryKey: ['tasks', sessionId, selectedCwdRef.current] });\n});\n```\n\n## Key Invariant\n\n`statusRef` is already maintained at line 134-137:\n```typescript\nconst statusRef = useRef(status);\nuseEffect(() => {\n  statusRef.current = status;\n});\n```\nThis synchronous effect (no dependency array means it runs after every render) ensures `statusRef.current` always reflects the latest `status` value. The guard `statusRef.current === 'streaming'` is safe to use inside the closure.\n\n## Invariant Preserved\n\nWhen `sync_update` fires after the `done` event transitions status to `'idle'`, `statusRef.current` will be `'idle'`, the guard will not return early, and `invalidateQueries()` will fire — post-stream history sync is unaffected.\n\n## Acceptance Criteria\n\n- The `sync_update` listener body is NOT reached when `statusRef.current === 'streaming'`\n- The `sync_update` listener body IS reached when `statusRef.current === 'idle'`\n- No new state, refs, or imports are required — `statusRef` is already in scope\n- The change is exactly 1 inserted line (`if (statusRef.current === 'streaming') return;`) plus a code comment\n- All existing relay tests in `apps/client/src/layers/features/chat/model/__tests__/use-chat-session-relay.test.ts` continue to pass",
      "activeForm": "Guarding sync_update invalidation during streaming",
      "size": "small",
      "priority": "high",
      "dependencies": [],
      "parallelWith": ["1.2", "1.3"]
    },
    {
      "id": "1.2",
      "phase": 1,
      "phaseName": "Client-Side Bug Fixes",
      "subject": "[fix-relay-streaming-bugs] [P1] Replace length-based history slice with ID-set deduplication",
      "description": "Fix Bug 1 (message duplication) — Layer 2: Replace the index-based history merge in the seed effect with an ID-set filter in `apps/client/src/layers/features/chat/model/use-chat-session.ts`.\n\n## Problem\n\nThe current seed effect (lines 210-217) uses `history.slice(currentMessages.length)` to find new messages to append. This assumes no overlap between local streaming state and server history — an assumption that fails under any timing race. If the history refetch completes during the streaming→idle transition window, `currentMessages.length` may not accurately reflect which messages are already rendered locally, causing already-streamed content to be appended again.\n\n## Fix\n\nReplace the slice-based merge with an ID-set filter. `HistoryMessage.id` is a stable UUID present on all history messages (confirmed by `mapHistoryMessage()` at line 69: `id: m.id`).\n\n**File:** `apps/client/src/layers/features/chat/model/use-chat-session.ts`\n**Lines to change:** 210-217\n\n```typescript\n// BEFORE:\nif (historySeededRef.current && !isStreaming) {\n  const currentMessages = messagesRef.current;\n  const newMessages = history.slice(currentMessages.length);\n\n  if (newMessages.length > 0) {\n    setMessages((prev) => [...prev, ...newMessages.map(mapHistoryMessage)]);\n  }\n}\n\n// AFTER:\nif (historySeededRef.current && !isStreaming) {\n  const currentIds = new Set(messagesRef.current.map((m) => m.id));\n  const newMessages = history.filter((m) => !currentIds.has(m.id));\n\n  if (newMessages.length > 0) {\n    setMessages((prev) => [...prev, ...newMessages.map(mapHistoryMessage)]);\n  }\n}\n```\n\n## Why Both Layers Are Needed\n\nTask 1.1 eliminates the unnecessary refetch during streaming (the root cause). This task eliminates duplicate rendering even if a refetch does complete during the streaming→idle transition window — defense in depth against any timing race, not just the `sync_update` race.\n\n## Performance Notes\n\n`new Set(messagesRef.current.map(...))` runs on every `historyQuery.data` change. With typical session message counts (< 200 per session), this is O(n) and negligible. No memoization is needed.\n\n## Acceptance Criteria\n\n- The seed effect uses `currentIds` Set + `.filter()` instead of `.slice(currentMessages.length)`\n- Messages already present in local state (by `id`) are never appended from history\n- New messages (IDs not in local state) are still correctly appended\n- The `messagesRef` ref is already maintained by the hook — no new refs required\n- All existing relay and legacy tests continue to pass\n- Manually verify: if `history = [A, B, C]` and `messagesRef.current = [A, B]`, only `C` is appended",
      "activeForm": "Replacing length-based slice with ID-set deduplication",
      "size": "small",
      "priority": "high",
      "dependencies": [],
      "parallelWith": ["1.1", "1.3"]
    },
    {
      "id": "1.3",
      "phase": 1,
      "phaseName": "Client-Side Bug Fixes",
      "subject": "[fix-relay-streaming-bugs] [P1] Disable historyQuery polling in Relay mode",
      "description": "Fix Bug 2 (503 storm) — Layer 1: Extend the `refetchInterval` guard in `historyQuery` to also return `false` when Relay mode is active in `apps/client/src/layers/features/chat/model/use-chat-session.ts`.\n\n## Problem\n\nIn Relay mode, `sync_update` SSE events from the persistent EventSource already drive all history invalidation via `queryClient.invalidateQueries()`. The `refetchInterval` polling (every 3 seconds on an active tab) is entirely redundant. Each poll hits `GET /api/sessions/:id/messages`, which must read the SDK JSONL transcript file. Under Relay-mode load, these repeated reads contribute to the 503 storm.\n\n## Fix\n\nAdd `|| relayEnabled` to the existing `isStreaming` guard so the interval returns `false` for the entire Relay session — both during and between streaming.\n\n`relayEnabled` is already in scope at line 85: `const relayEnabled = useRelayEnabled();`\n\n**File:** `apps/client/src/layers/features/chat/model/use-chat-session.ts`\n**Lines to change:** 184-189\n\n```typescript\n// BEFORE:\nrefetchInterval: () => {\n  if (isStreaming) return false;\n  return isTabVisible\n    ? QUERY_TIMING.ACTIVE_TAB_REFETCH_MS\n    : QUERY_TIMING.BACKGROUND_TAB_REFETCH_MS;\n},\n\n// AFTER:\nrefetchInterval: () => {\n  // In Relay mode, sync_update SSE events drive invalidation — polling is redundant\n  if (isStreaming || relayEnabled) return false;\n  return isTabVisible\n    ? QUERY_TIMING.ACTIVE_TAB_REFETCH_MS\n    : QUERY_TIMING.BACKGROUND_TAB_REFETCH_MS;\n},\n```\n\n## TanStack Query v5 Constraint — Critical\n\nUse `refetchInterval: () => false` — NOT `enabled: false`. In TanStack Query v5, setting `enabled: false` causes the query to silently ignore `invalidateQueries()` and `refetchQueries()` calls. This would break post-stream history sync (when `sync_update` fires after streaming completes, the invalidation would have no effect). The function form of `refetchInterval` returning `false` correctly disables polling while preserving `invalidateQueries()` reactivity.\n\nReference: https://tanstack.com/query/v5/docs/framework/react/guides/disabling-queries — \"When enabled is false, the query will ignore query client invalidateQueries and refetchQueries calls\"\n\n## EventSource Loss Coverage\n\nIf the EventSource disconnects in Relay mode, it auto-reconnects (browser standard behavior). The staleness detector (lines 220-242) provides a 15-second fallback: if no events arrive for 15s, it polls `transport.getSession()` and invalidates history on recovery. This covers the edge case where `sync_update` events are missed during a reconnect window.\n\n## Acceptance Criteria\n\n- When `relayEnabled` is `true`, `refetchInterval` returns `false` regardless of `isStreaming` value\n- When `relayEnabled` is `false`, the original polling behavior is preserved (returns interval based on tab visibility)\n- `invalidateQueries()` calls still trigger refetches in Relay mode (proving `enabled: false` was NOT used)\n- No new imports required — `relayEnabled` and `useRelayEnabled` are already in scope\n- All existing relay and legacy tests continue to pass",
      "activeForm": "Disabling historyQuery polling in Relay mode",
      "size": "small",
      "priority": "high",
      "dependencies": [],
      "parallelWith": ["1.1", "1.2"]
    },
    {
      "id": "1.4",
      "phase": 1,
      "phaseName": "Server-Side Bug Fix",
      "subject": "[fix-relay-streaming-bugs] [P1] Add try/catch to GET /messages Express route handler",
      "description": "Fix Bug 2 (503 storm) — Layer 2: Wrap the `GET /:id/messages` handler body in try/catch with `next(err)` in `apps/server/src/routes/sessions.ts`.\n\n## Problem\n\nExpress 4 does not automatically forward unhandled async rejections in route handlers to error middleware. When `runtime.getMessageHistory()` or `runtime.getSessionETag()` throws (e.g., due to transcript I/O contention, session write lock, or Relay-mode state conflict), the request hangs with no response. A proxy timeout then returns a 503 to the client. This is a latent correctness bug that surfaces under Relay-mode polling volume.\n\nNote: Express 5 fixes this by automatically calling `next(err)` for unhandled promise rejections in async routes. DorkOS uses Express 4.\n\n## Fix\n\nAdd `next` parameter to the route handler signature and wrap the async body in try/catch.\n\n**File:** `apps/server/src/routes/sessions.ts`\n**Lines to change:** 116-139 (GET `/:id/messages` handler)\n\n```typescript\n// BEFORE:\nrouter.get('/:id/messages', async (req, res) => {\n  const sessionId = parseSessionId(req.params.id);\n  if (!sessionId) return sendError(res, 400, 'Invalid session ID', 'INVALID_SESSION_ID');\n\n  const cwdParam = (req.query.cwd as string) || undefined;\n  if (!(await assertBoundary(cwdParam, res))) return;\n  const cwd = cwdParam || vaultRoot;\n\n  const runtime = runtimeRegistry.getDefault();\n  const internalSessionId = runtime.getInternalSessionId(sessionId) ?? sessionId;\n\n  const etag = await runtime.getSessionETag(cwd, internalSessionId);\n  if (etag) {\n    res.setHeader('ETag', etag);\n    if (req.headers['if-none-match'] === etag) {\n      return res.status(304).end();\n    }\n  }\n\n  const messages = await runtime.getMessageHistory(cwd, internalSessionId);\n  res.json({ messages });\n});\n\n// AFTER:\nrouter.get('/:id/messages', async (req, res, next) => {\n  const sessionId = parseSessionId(req.params.id);\n  if (!sessionId) return sendError(res, 400, 'Invalid session ID', 'INVALID_SESSION_ID');\n\n  const cwdParam = (req.query.cwd as string) || undefined;\n  if (!(await assertBoundary(cwdParam, res))) return;\n  const cwd = cwdParam || vaultRoot;\n\n  try {\n    const runtime = runtimeRegistry.getDefault();\n    const internalSessionId = runtime.getInternalSessionId(sessionId) ?? sessionId;\n\n    const etag = await runtime.getSessionETag(cwd, internalSessionId);\n    if (etag) {\n      res.setHeader('ETag', etag);\n      if (req.headers['if-none-match'] === etag) {\n        return res.status(304).end();\n      }\n    }\n\n    const messages = await runtime.getMessageHistory(cwd, internalSessionId);\n    res.json({ messages });\n  } catch (err) {\n    next(err);\n  }\n});\n```\n\n## Scope\n\nThis fix applies to all callers, not just Relay-mode polling. Any future error condition that causes `getMessageHistory` or `getSessionETag` to throw will return a proper 500 response immediately instead of hanging.\n\nNote: The `assertBoundary(cwdParam, res)` check remains OUTSIDE the try/catch block intentionally — it handles its own error response internally and returns `false` on failure. Moving it inside the try/catch would not break behavior but would be unnecessary.\n\n## Acceptance Criteria\n\n- The route handler signature includes `next` as the third parameter\n- `runtime.getDefault()`, `getSessionETag()`, and `getMessageHistory()` calls are all inside the try/catch\n- When `getMessageHistory` throws, `next(err)` is called and Express error middleware returns 500\n- When `getSessionETag` throws, `next(err)` is called and Express error middleware returns 500\n- The 304 ETag path continues to work correctly\n- All existing `sessions.test.ts` success-path tests pass unchanged",
      "activeForm": "Adding error handling to GET /messages route handler",
      "size": "small",
      "priority": "high",
      "dependencies": [],
      "parallelWith": ["1.1", "1.2", "1.3"]
    },
    {
      "id": "2.1",
      "phase": 2,
      "phaseName": "Tests",
      "subject": "[fix-relay-streaming-bugs] [P2] Add sync_update guard tests to relay test suite",
      "description": "Add two test cases to `apps/client/src/layers/features/chat/model/__tests__/use-chat-session-relay.test.ts` that verify the `sync_update` streaming guard (Task 1.1) and the ID-set deduplication (Task 1.2) work correctly.\n\n## Test File Location\n\n`apps/client/src/layers/features/chat/model/__tests__/use-chat-session-relay.test.ts`\n\nAdd two `it()` blocks inside the existing `describe('useChatSession relay protocol', ...)` suite. Do NOT create a new file — append to the existing suite.\n\n## Test 1: sync_update does NOT invalidate during streaming\n\nThis test verifies the `statusRef.current === 'streaming'` guard prevents premature history invalidation.\n\n```typescript\nit('does not call invalidateQueries on sync_update while streaming', async () => {\n  mockUseRelayEnabled.mockReturnValue(true);\n  vi.mocked(mockTransport.sendMessageRelay).mockResolvedValue({\n    messageId: 'msg-1',\n    traceId: 'trace-1',\n  });\n\n  // Use a real QueryClient so we can spy on invalidateQueries\n  const queryClient = new QueryClient({\n    defaultOptions: { queries: { retry: false } },\n  });\n  const invalidateSpy = vi.spyOn(queryClient, 'invalidateQueries');\n\n  function WrapperWithQueryClient({ children }: { children: React.ReactNode }) {\n    return React.createElement(\n      QueryClientProvider,\n      { client: queryClient },\n      React.createElement(TransportProvider as any, { transport: mockTransport }, children)\n    );\n  }\n\n  const { result } = renderHook(() => useChatSession('session-1'), {\n    wrapper: WrapperWithQueryClient,\n  });\n\n  // Emit stream_ready so handleSubmit doesn't block on the 5s timeout\n  act(() => {\n    const es = MockEventSource.instances[0];\n    es?.emit('stream_ready', { clientId: 'test-uuid-1' });\n  });\n\n  // Submit to put hook into 'streaming' state\n  act(() => { result.current.setInput('hello'); });\n  await act(async () => { await result.current.handleSubmit(); });\n\n  // Confirm status is 'streaming'\n  expect(result.current.status).toBe('streaming');\n\n  // Clear any invalidations from the submit path\n  invalidateSpy.mockClear();\n\n  // Fire sync_update while streaming\n  act(() => {\n    const es = MockEventSource.instances[0];\n    es?.emit('sync_update', {});\n  });\n\n  // invalidateQueries should NOT have been called — guard returns early\n  expect(invalidateSpy).not.toHaveBeenCalled();\n});\n```\n\n## Test 2: sync_update DOES invalidate after streaming completes\n\nThis test verifies history sync still works post-stream. Guards against overly aggressive fixes that skip all invalidation.\n\n```typescript\nit('calls invalidateQueries on sync_update when status is idle', async () => {\n  mockUseRelayEnabled.mockReturnValue(true);\n\n  // Use a real QueryClient so we can spy on invalidateQueries\n  const queryClient = new QueryClient({\n    defaultOptions: { queries: { retry: false } },\n  });\n  const invalidateSpy = vi.spyOn(queryClient, 'invalidateQueries');\n\n  function WrapperWithQueryClient({ children }: { children: React.ReactNode }) {\n    return React.createElement(\n      QueryClientProvider,\n      { client: queryClient },\n      React.createElement(TransportProvider as any, { transport: mockTransport }, children)\n    );\n  }\n\n  renderHook(() => useChatSession('session-1'), {\n    wrapper: WrapperWithQueryClient,\n  });\n\n  // No submit — hook is in 'idle' state on mount\n  // Clear any invalidations from mount/query setup\n  invalidateSpy.mockClear();\n\n  // Fire sync_update while idle\n  act(() => {\n    const es = MockEventSource.instances[0];\n    es?.emit('sync_update', {});\n  });\n\n  // invalidateQueries SHOULD have been called — status is 'idle', guard does not return early\n  expect(invalidateSpy).toHaveBeenCalledWith(\n    expect.objectContaining({\n      queryKey: ['messages', 'session-1', expect.anything()],\n    })\n  );\n});\n```\n\n## Existing test infrastructure to reuse\n\nThe test file already provides:\n- `MockEventSource` class with `emit()` helper and `static instances[]`\n- `createWrapper(transport)` factory (uses `new QueryClient` internally)\n- `vi.mock('@/layers/entities/relay', ...)` for `mockUseRelayEnabled`\n- `createMockTransport()` from `@dorkos/test-utils`\n\nThe new tests need their own `QueryClient` instances (to spy on `invalidateQueries`) rather than using `createWrapper()`. This is explicitly noted in the spec: \"Client tests: `queryClient` should be a real `QueryClient` instance from `@tanstack/react-query` (not mocked), so `invalidateQueries` spy can be asserted\".\n\n## Acceptance Criteria\n\n- Both tests pass with the guards from Tasks 1.1 and 1.2 in place\n- Test 1 FAILS if the `if (statusRef.current === 'streaming') return;` guard is removed\n- Test 2 FAILS if `invalidateQueries` is never called regardless of status\n- No new mocks or test utilities are required beyond what already exists in the file\n- Running `pnpm vitest run apps/client/src/layers/features/chat/model/__tests__/use-chat-session-relay.test.ts` passes all tests",
      "activeForm": "Adding sync_update guard tests to relay test suite",
      "size": "medium",
      "priority": "medium",
      "dependencies": ["1.1", "1.2"],
      "parallelWith": ["2.2"]
    },
    {
      "id": "2.2",
      "phase": 2,
      "phaseName": "Tests",
      "subject": "[fix-relay-streaming-bugs] [P2] Add GET /messages error-handling test to sessions test suite",
      "description": "Add one test case to `apps/server/src/routes/__tests__/sessions.test.ts` that verifies Express returns 500 instead of hanging when `getMessageHistory` throws (Task 1.4).\n\n## Test File Location\n\n`apps/server/src/routes/__tests__/sessions.test.ts`\n\nAdd one `it()` block inside the existing `describe` structure. Identify the correct describe block for GET /messages tests by looking at the existing test structure. Do NOT create a new file.\n\n## Test\n\n```typescript\nit('returns 500 when getMessageHistory throws', async () => {\n  // Mock runtime to throw on getMessageHistory\n  mockRuntime.getMessageHistory.mockRejectedValueOnce(new Error('I/O error'));\n\n  const res = await request(app)\n    .get(`/api/sessions/${S1}/messages`)\n    .set('x-client-id', 'test-client');\n\n  expect(res.status).toBe(500);\n  // Should have an error field in the response body\n  expect(res.body).toHaveProperty('error');\n});\n```\n\n## Existing test infrastructure to reuse\n\nThe test file already provides:\n- `mockRuntime` object with all `AgentRuntime` methods mocked via `vi.fn()`\n- `S1` constant: `'00000000-0000-4000-8000-000000000001'` — valid UUID for session ID\n- `request(app)` via `supertest` — already imported\n- `mockRuntime.getMessageHistory` is already a `vi.fn()` — use `.mockRejectedValueOnce()`\n- `createApp()` is already called at module level — `app` is already available\n\n## Validating the fix\n\nThis test should FAIL before Task 1.4 is applied (the request would hang until a timeout, or return an unexpected status). After Task 1.4 wraps the handler in try/catch with `next(err)`, Express error middleware sends a 500 response immediately.\n\n## Acceptance Criteria\n\n- The test passes after Task 1.4 is applied\n- The test FAILS (or hangs) if the try/catch from Task 1.4 is removed\n- Response status is `500` (not `503` or a timeout)\n- Response body contains an `error` field\n- All other existing `sessions.test.ts` tests continue to pass\n- Running `pnpm vitest run apps/server/src/routes/__tests__/sessions.test.ts` passes all tests",
      "activeForm": "Adding error-handling test for GET /messages route",
      "size": "small",
      "priority": "medium",
      "dependencies": ["1.4"],
      "parallelWith": ["2.1"]
    },
    {
      "id": "2.3",
      "phase": 2,
      "phaseName": "Tests",
      "subject": "[fix-relay-streaming-bugs] [P2] Run full test suite and verify all tests pass",
      "description": "Run the full `pnpm test` suite to confirm all changes are correct and no regressions were introduced.\n\n## Commands to run\n\n```bash\n# Run full test suite across client + server\npnpm test -- --run\n\n# Or run just the affected test files for faster feedback:\npnpm vitest run apps/client/src/layers/features/chat/model/__tests__/use-chat-session-relay.test.ts\npnpm vitest run apps/server/src/routes/__tests__/sessions.test.ts\n```\n\n## Expected results\n\n### Tests that must pass (existing, no behavioral change)\n\n**Client relay tests** (`use-chat-session-relay.test.ts`):\n- `calls sendMessageRelay when relay enabled`\n- `calls sendMessage when relay disabled`\n- `adds user message optimistically on relay submit`\n- `sets status to streaming on relay submit`\n- `handles sendMessageRelay errors`\n- `processes relay_message events from EventSource`\n- `relay EventSource is NOT torn down when isStreaming changes`\n- `relay EventSource listens for stream_ready and registers it`\n- `relay EventSource URL includes clientId`\n- `legacy path does NOT create EventSource when relay enabled`\n- `legacy path creates EventSource without clientId when relay disabled`\n- All staleness detector tests\n\n**Server sessions tests** (`sessions.test.ts`):\n- All existing GET /messages success-path tests (200, 304 ETag path)\n- All other route tests in sessions.test.ts\n\n### New tests that must pass (added in Tasks 2.1 and 2.2)\n\n- `does not call invalidateQueries on sync_update while streaming`\n- `calls invalidateQueries on sync_update when status is idle`\n- `returns 500 when getMessageHistory throws`\n\n## If any test fails\n\n1. Run the failing test file in isolation to see the full error\n2. Check that the code changes from Phase 1 match the exact before/after shown in the spec\n3. Verify `statusRef` is being read correctly (not `isStreaming` closure value)\n4. Verify the `next` parameter is added to the Express route handler signature\n\n## Acceptance Criteria\n\n- `pnpm test -- --run` exits with code 0\n- No test regressions in any package\n- All 3 new tests pass\n- TypeScript compilation passes: `pnpm typecheck`",
      "activeForm": "Running full test suite to verify no regressions",
      "size": "small",
      "priority": "medium",
      "dependencies": ["2.1", "2.2"],
      "parallelWith": []
    }
  ]
}
